lark_ag/__init__.py
lark_ag/lark_ag.py
lark_ag/generator_layer/__init__.py
lark_ag/generator_layer/ag_parser.py
lark_ag/generator_layer/generator_layer.py
lark_ag/generator_layer/grammar.lark
lark_ag/generator_layer/interpreter_generator.py
lark_ag/processor_layer/__init__.py
lark_ag/processor_layer/processor_layer.py
lark_ag-1.0.2.dist-info/LICENSE
lark_ag-1.0.2.dist-info/WHEEL
lark_ag-1.0.2.dist-info/METADATA
lark_ag-1.0.2.dist-info/RECORD
