Metadata-Version: 2.1
Name: lark-ag
Version: 1.0.2
Summary: LARK-AG: A Python library for providing Attribute Grammar support to Lark. 
Author-email: Daniel Faria <danielfaria089@gmail.com>
Classifier: License :: OSI Approved :: MIT License
Requires-Dist: lark >=1.1.9
